{
  "Version": 241,
  "ExportDate": "2025-06-04T11:10:18.6919868-03:00",
  "ChangeType": "Added",
  "Id": "12141013",
  "Name": "Phoenix Drive VI",
  "Job": "Blaze Wizard",
  "Desc": "Throws a barrage of flames forward, completely engulfing enemies. <span style=\"font-weight:bold; color:orange;\">Use with the Up, Down, Left, and Right keys to direct the flames in any direction.</span><br />After a certain number of hits with the Incarnate's blessing, the Fox's Mischief debuff is activated.<br />When Fox's Mischief stacks <span style=\"font-weight:bold; color:orange;\">5 times, you can hit it with Inferno Rise - Fox to explode it. This is a Fire Element attack.</span>",
  "Coordinates": {
    "lt": {},
    "rb": {}
  },
  "Fields": {
    "type": "1",
    "magicDamage": "1",
    "areaAttack": "1",
    "req/12121054": "1",
    "action/0": "6thPhoenixDriveOrb",
    "common/maxLevel": "30",
    "common/mpCon": "34+d(x/7)",
    "common/damage": "465+19*x",
    "common/attackCount": "2",
    "common/mobCount": "8",
    "common/x": "8",
    "common/range": "300",
    "common/bulletCount": "4",
    "common/z": "30",
    "common/y": "210",
    "common/w": "5",
    "common/ballDelay": "120",
    "common/w2": "20",
    "common/q2": "50",
    "skillList/0": "400021000",
    "elemAttr": "f",
    "weapon": "37",
    "weapon2": "38",
    "invisible": "1",
    "id": "12141013",
    "has_req": true,
    "has_weapon": true,
    "voice/prop": "25",
    "voice/male/count": 6,
    "voice/female/count": 6,
    "voice/male/path/0": "{ Old = , New = flameWizard/M/122 }",
    "voice/male/path/1": "{ Old = , New = flameWizard/M/123 }",
    "voice/male/path/2": "{ Old = , New = flameWizard/M/124 }",
    "voice/male/path/3": "{ Old = , New = flameWizard/M/17 }",
    "voice/male/path/4": "{ Old = , New = flameWizard/M/12 }",
    "voice/male/path/5": "{ Old = , New = flameWizard/M/41 }",
    "voice/female/path/0": "{ Old = , New = flameWizard/F/94 }",
    "voice/female/path/1": "{ Old = , New = flameWizard/F/95 }",
    "voice/female/path/2": "{ Old = , New = flameWizard/F/96 }",
    "voice/female/path/3": "{ Old = , New = flameWizard/F/47 }",
    "voice/female/path/4": "{ Old = , New = flameWizard/F/49 }",
    "voice/female/path/5": "{ Old = , New = flameWizard/F/14 }"
  },
  "HFields": {
    "h1": "MP Cost: 38. Fires 4 flames that attack up to 8 enemies at 1035% Damage 2 times. If a single enemy is hit by multiple flames, Final Damage -50% for each subsequent flame after the first one."
  },
  "Icons": {
    "IconPath": "Icons/New/v241_12141013_icon.png",
    "IconPathOld": null
  },
  "Animations": {
    "effect": {
      "Old": null,
      "New": "Animations/New/12141013_effect_new.webp"
    },
    "effect0": {
      "Old": null,
      "New": "Animations/New/12141013_effect0_new.webp"
    }
  },
  "Voices": {
    "M5": {
      "OldPath": null,
      "NewPath": "Voices/New/12141013_voice_M5.mp3",
      "Gender": "M",
      "HasChanged": true,
      "IsNew": true
    },
    "M4": {
      "OldPath": null,
      "NewPath": "Voices/New/12141013_voice_M4.mp3",
      "Gender": "M",
      "HasChanged": true,
      "IsNew": true
    },
    "M3": {
      "OldPath": null,
      "NewPath": "Voices/New/12141013_voice_M3.mp3",
      "Gender": "M",
      "HasChanged": true,
      "IsNew": true
    },
    "M2": {
      "OldPath": null,
      "NewPath": "Voices/New/12141013_voice_M2.mp3",
      "Gender": "M",
      "HasChanged": true,
      "IsNew": true
    },
    "M1": {
      "OldPath": null,
      "NewPath": "Voices/New/12141013_voice_M1.mp3",
      "Gender": "M",
      "HasChanged": true,
      "IsNew": true
    },
    "M0": {
      "OldPath": null,
      "NewPath": "Voices/New/12141013_voice_M0.mp3",
      "Gender": "M",
      "HasChanged": true,
      "IsNew": true
    },
    "F5": {
      "OldPath": null,
      "NewPath": "Voices/New/12141013_voice_F5.mp3",
      "Gender": "F",
      "HasChanged": true,
      "IsNew": true
    },
    "F4": {
      "OldPath": null,
      "NewPath": "Voices/New/12141013_voice_F4.mp3",
      "Gender": "F",
      "HasChanged": true,
      "IsNew": true
    },
    "F3": {
      "OldPath": null,
      "NewPath": "Voices/New/12141013_voice_F3.mp3",
      "Gender": "F",
      "HasChanged": true,
      "IsNew": true
    },
    "F2": {
      "OldPath": null,
      "NewPath": "Voices/New/12141013_voice_F2.mp3",
      "Gender": "F",
      "HasChanged": true,
      "IsNew": true
    },
    "F1": {
      "OldPath": null,
      "NewPath": "Voices/New/12141013_voice_F1.mp3",
      "Gender": "F",
      "HasChanged": true,
      "IsNew": true
    },
    "F0": {
      "OldPath": null,
      "NewPath": "Voices/New/12141013_voice_F0.mp3",
      "Gender": "F",
      "HasChanged": true,
      "IsNew": true
    }
  }
}