{
  "Version": 241,
  "ExportDate": "2025-06-04T11:10:18.801743-03:00",
  "ChangeType": "Added",
  "Id": "13141008",
  "Name": "Anemoi",
  "Job": "Wind Archer",
  "Desc": "Moved by the fighting spirit of the wind spirits, the Great Spirit appears and brings the wind of victory. Anemoi periodically waves her hand to summon a powerful gust of wind to attack.",
  "Coordinates": {
    "lt": {
      "x": -520,
      "y": -280
    },
    "rb": {
      "x": 50,
      "y": 80
    }
  },
  "Fields": {
    "type": "1",
    "info2/ignoreCounter": "1",
    "common/maxLevel": "30",
    "common/damage": "949+31*x",
    "common/attackCount": "10",
    "common/mobCount": "10",
    "common/time": "20",
    "common/subTime": "1200",
    "common/lt/x": -520,
    "common/lt/y": -280,
    "common/rb/x": 50,
    "common/rb/y": 80,
    "common/x": "1360",
    "common/y": "-100",
    "hit/0/pos": "10",
    "hit/0/z": "1",
    "hit/0/useZ": "1",
    "hit/0/randomDelayedTimeStart": "450",
    "hit/0/randomDelayedTimeEnd": "600",
    "hit/0/randomHitOriginX": "60",
    "hit/0/randomHitOriginY": "30",
    "hit/1/pos": "10",
    "hit/1/z": "1",
    "hit/1/useZ": "1",
    "hit/1/randomDelayedTimeStart": "450",
    "hit/1/randomDelayedTimeEnd": "600",
    "hit/1/randomHitOriginX": "60",
    "hit/1/randomHitOriginY": "30",
    "hit/2/pos": "10",
    "hit/2/z": "1",
    "hit/2/useZ": "1",
    "hit/2/randomDelayedTimeStart": "450",
    "hit/2/randomDelayedTimeEnd": "600",
    "hit/2/randomHitOriginX": "60",
    "hit/2/randomHitOriginY": "30",
    "hit/3/pos": "10",
    "hit/3/z": "1",
    "hit/3/useZ": "1",
    "hit/3/randomDelayedTimeStart": "450",
    "hit/3/randomDelayedTimeEnd": "600",
    "hit/3/randomHitOriginX": "60",
    "hit/3/randomHitOriginY": "30",
    "hit/4/pos": "10",
    "hit/4/z": "1",
    "hit/4/useZ": "1",
    "hit/4/randomDelayedTimeStart": "450",
    "hit/4/randomDelayedTimeEnd": "600",
    "hit/4/randomHitOriginX": "60",
    "hit/4/randomHitOriginY": "30",
    "hit/5/pos": "10",
    "hit/5/z": "1",
    "hit/5/useZ": "1",
    "hit/5/randomDelayedTimeStart": "450",
    "hit/5/randomDelayedTimeEnd": "600",
    "hit/5/randomHitOriginX": "60",
    "hit/5/randomHitOriginY": "30",
    "hit/randomHit": "1",
    "invisible": "1",
    "notIncBuffDuration": "1",
    "id": "13141008",
    "common/lt": "WzComparerR2.WzLib.Wz_Vector",
    "common/rb": "WzComparerR2.WzLib.Wz_Vector"
  },
  "HFields": {},
  "Icons": {
    "IconPath": "Icons/New/v241_13141008_icon.png",
    "IconPathOld": null
  },
  "Animations": {
    "hit": {
      "Old": null,
      "New": "Animations/New/13141008_hit_new.webp"
    }
  },
  "Voices": {}
}