{
  "Version": 241,
  "ExportDate": "2025-06-04T11:10:07.021559-03:00",
  "ChangeType": "Changed",
  "Id": "155121202",
  "Name": "Uncontrollable Chaos",
  "Job": "Ark",
  "Desc": "Moves rapidly to slash open all sides.<br />Changes to Abyss Charge Drive in Flora form.",
  "Coordinates": {
    "lt": {},
    "rb": {}
  },
  "Fields": {
    "cancelableSkillID/7": {
      "Old": null,
      "New": "155141029"
    },
    "cancelableSkillID/8": {
      "Old": null,
      "New": "155141031"
    },
    "cancelableSkillID/9": {
      "Old": null,
      "New": "155141036"
    }
  },
  "HFields": {},
  "Icons": {
    "IconPath": "Icons/New/v241_155121202_icon.png",
    "IconPathOld": null
  },
  "Animations": {},
  "Voices": {}
}