{
  "Version": 241,
  "ExportDate": "2025-06-04T11:10:09.5811288-03:00",
  "ChangeType": "Changed",
  "Id": "32100010",
  "Name": "Death Contract",
  "Job": "Battle Mage",
  "Desc": "Reinforces your contract with the grim reaper.",
  "Coordinates": {
    "lt": {},
    "rb": {}
  },
  "Fields": {
    "resummonByUnionCharTag": {
      "Old": null,
      "New": "1"
    }
  },
  "HFields": {},
  "Icons": {
    "IconPath": "Icons/New/v241_32100010_icon.png",
    "IconPathOld": null
  },
  "Animations": {},
  "Voices": {}
}