{
  "Version": 241,
  "ExportDate": "2025-06-04T11:10:15.1545623-03:00",
  "ChangeType": "Changed",
  "Id": "80001341",
  "Name": "Bombing! That is me.",
  "Job": "Etc",
  "Desc": "Summons the Traitor Magnus to fight together. (Be careful not to get betrayed...) The Soul Weapon's power temporarily summons Magnus to attack nearby monsters.",
  "Coordinates": {
    "lt": {},
    "rb": {}
  },
  "Fields": {
    "resetByUnionCharTag": {
      "Old": null,
      "New": "1"
    }
  },
  "HFields": {},
  "Icons": {
    "IconPath": "Icons/New/v241_80001341_icon.png",
    "IconPathOld": null
  },
  "Animations": {},
  "Voices": {}
}